{
	"configurations" : 
	[
		{
			"directories" : 
			[
				{
					"build" : ".",
					"jsonFile" : "directory-.-Debug-d0094a50bb2071803777.json",
					"minimumCMakeVersion" : 
					{
						"string" : "3.26"
					},
					"projectIndex" : 0,
					"source" : ".",
					"targetIndexes" : 
					[
						0,
						1
					]
				}
			],
			"name" : "Debug",
			"projects" : 
			[
				{
					"directoryIndexes" : 
					[
						0
					],
					"name" : "Machine_GUI",
					"targetIndexes" : 
					[
						0,
						1
					]
				}
			],
			"targets" : 
			[
				{
					"directoryIndex" : 0,
					"id" : "Machine_GUI::@6890427a1f51a3e7e1df",
					"jsonFile" : "target-Machine_GUI-Debug-0dd092b45e594a3cd3e3.json",
					"name" : "Machine_GUI",
					"projectIndex" : 0
				},
				{
					"directoryIndex" : 0,
					"id" : "Machine_GUI_autogen::@6890427a1f51a3e7e1df",
					"jsonFile" : "target-Machine_GUI_autogen-Debug-5d1e4cac715dc4af3510.json",
					"name" : "Machine_GUI_autogen",
					"projectIndex" : 0
				}
			]
		}
	],
	"kind" : "codemodel",
	"paths" : 
	{
		"build" : "D:/Clion_Project/Machine_GUI/cmake-build-debug",
		"source" : "D:/Clion_Project/Machine_GUI"
	},
	"version" : 
	{
		"major" : 2,
		"minor" : 5
	}
}
